pymium/__init__.py
pymium/pymium.py
pymium/core/__init__.py
pymium/core/core.py
pymium/core/assets/__init__.py
pymium/core/assets/templates/__init__.py
pymium/core/assets/templates/templates.py
pymium/core/base/__init__.py
pymium/core/base/prebuilt_types.py
pymium/core/base/types.py
pymium/core/base/style/__init__.py
pymium/core/base/style/style.py
pymium/core/element/__init__.py
pymium/core/element/element.py
pymium/core/element/handler.py
pymium-0.4.0.dist-info/LICENSE
pymium-0.4.0.dist-info/METADATA
pymium-0.4.0.dist-info/WHEEL
pymium-0.4.0.dist-info/top_level.txt
pymium-0.4.0.dist-info/RECORD
