Metadata-Version: 2.1
Name: pymium
Version: 0.4.0
Summary: Windows application creator
Author: Z3N
Author-email: iliya.souri7890@example.com
Classifier: Programming Language :: Python :: 3
Classifier: License :: OSI Approved :: MIT License
Classifier: Operating System :: OS Independent
Requires-Python: >=3.11
License-File: LICENSE
Requires-Dist: pywebview
